pelican/plugins/linkbacks/__init__.py
pelican/plugins/linkbacks/linkbacks.py
pelican/plugins/linkbacks/test_content/dummy_article.md
pelican/plugins/linkbacks/test_linkbacks.py
pelican_plugin_linkbacks-1.0.6.dist-info/METADATA
pelican_plugin_linkbacks-1.0.6.dist-info/WHEEL
pelican_plugin_linkbacks-1.0.6.dist-info/licenses/LICENSE.txt
pelican_plugin_linkbacks-1.0.6.dist-info/RECORD
