Metadata-Version: 2.4
Name: pelican-plugin-linkbacks
Version: 1.0.6
Summary: Pelican plugin implementing Linkback protocols, on the linking server side
License-Expression: AGPL-3.0
License-File: LICENSE.txt
Keywords: pelican,plugin,linkback,pingback,trackback,webmention
Author: Lucas Cimon (@Lucas-C)
Requires-Python: >=3.10, <=3.14
Classifier: Development Status :: 5 - Production/Stable
Classifier: Environment :: Console
Classifier: Framework :: Pelican
Classifier: Framework :: Pelican :: Plugins
Classifier: Intended Audience :: End Users/Desktop
Classifier: License :: OSI Approved :: GNU Affero General Public License v3
Classifier: Operating System :: OS Independent
Classifier: Topic :: Internet :: WWW/HTTP
Classifier: Topic :: Software Development :: Libraries :: Python Modules
Requires-Dist: beautifulsoup4 (>=4.14.3)
Requires-Dist: requests (>=2.32.5)
Project-URL: Documentation, https://docs.getpelican.com/
Project-URL: Source, https://github.com/pelican-plugins/linkbacks
Project-URL: Tracker, https://github.com/pelican-plugins/linkbacks/issues
